dkdc_util/__init__.py
dkdc_util/main.py
dkdc_util-0.0.4.dist-info/METADATA
dkdc_util-0.0.4.dist-info/WHEEL
dkdc_util-0.0.4.dist-info/top_level.txt
dkdc_util-0.0.4.dist-info/RECORD
